ci_pipe/__init__.py
ci_pipe/decorators.py
ci_pipe/multi_pipeline.py
ci_pipe/pipeline.py
ci_pipe/plotter.py
ci_pipe/schema_validator.py
ci_pipe/step.py
ci_pipe/errors/__init__.py
ci_pipe/errors/caiman_backend_not_configured_error.py
ci_pipe/errors/ci_pipe_error.py
ci_pipe/errors/defaults_after_step_error.py
ci_pipe/errors/isx_backend_not_configured_error.py
ci_pipe/errors/output_key_not_found_error.py
ci_pipe/errors/resume_execution_error.py
ci_pipe/modules/__init__.py
ci_pipe/modules/caiman_module.py
ci_pipe/modules/isx_module.py
ci_pipe/modules/multi_module_proxy.py
ci_pipe/trace/__init__.py
ci_pipe/trace/ci_pipe_trace.py
ci_pipe/trace/trace_repository.py
ci_pipe/trace/schema/__init__.py
ci_pipe/trace/schema/branch.py
ci_pipe/trace/schema/pipeline.py
ci_pipe/utils/__init__.py
ci_pipe/utils/config_defaults.py
ci_pipe/utils/project_template.py
cipipeline/__init__.py
cipipeline-0.2.1.dist-info/licenses/LICENSE
external_dependencies/__init__.py
external_dependencies/caiman/__init__.py
external_dependencies/caiman/in_memory_caiman.py
external_dependencies/caiman/mocked_cnmf_submodule.py
external_dependencies/caiman/mocked_motion_correct.py
external_dependencies/caiman/mocked_motion_correction_submodule.py
external_dependencies/caiman/mocked_movie.py
external_dependencies/caiman/mocked_source_extraction.py
external_dependencies/file_system/__init__.py
external_dependencies/file_system/file_system_interface.py
external_dependencies/file_system/in_memory_file_system.py
external_dependencies/file_system/persistent_file_system.py
external_dependencies/isx/__init__.py
external_dependencies/isx/in_memory_isx.py
cipipeline-0.2.1.dist-info/METADATA
cipipeline-0.2.1.dist-info/WHEEL
cipipeline-0.2.1.dist-info/top_level.txt
cipipeline-0.2.1.dist-info/RECORD
