Metadata-Version: 2.4
Name: cipipeline
Version: 0.2.1
Summary: CIPipeline is a tool to analyze and process Calcium Imaging data.
Author-email: Gonzalez Agustín <agngonzalez@fi.uba.ar>, Loyarte Iván <iloyarte@fi.uba.ar>, Rueda Nazarena <nrueda@fi.uba.ar>, Singer Joaquín <josinger@fi.uba.ar>
License: MIT License
Project-URL: Homepage, https://github.com/CGK-Laboratory/ci_pipe
Project-URL: Repository, https://github.com/CGK-Laboratory/ci_pipe
Requires-Python: <3.11,>=3.10
License-File: LICENSE
Requires-Dist: rich>=13.7.0
Requires-Dist: PyYAML>=6.0
Dynamic: license-file
